{
  "stepOne": [
    {
      "Summ": "5000",
      "Term": "12",
      "id": 1
    },
    {
      "Summ": "123",
      "Term": "12",
      "id": 2
    }
  ],
  "stepTwo": [
    {
      "INN": "3131121243",
      "Name": "Ivan",
      "Surname": "Petrov",
      "City": "San Francisco, CA, United States",
      "id": 1
    },
    {
      "INN": "1231231231",
      "Name": "Lkdsjf",
      "Surname": "Skdfj",
      "City": "Kaifeng, SC, China",
      "id": 2
    }
  ],
  "stepThree": [
    {
      "Summ": "5000",
      "Term": "12",
      "INN": "3131121243",
      "Surname": "Petrov",
      "City": "San Francisco, CA, United States",
      "id": 1
    }
  ]
}